Metadata-Version: 1.0
Name: python-oop
Version: 0.2
Summary: Gaussian distributions
Home-page: UNKNOWN
Author: Chetan Bhangale
Author-email: cbhangale4@gmail.com
License: UNKNOWN
Platform: UNKNOWN
